B3DB/B3DB_classification.tsv
B3DB/B3DB_classification_extended.tsv.gz
B3DB/B3DB_classification_external.tsv
B3DB/B3DB_regression.tsv
B3DB/B3DB_regression_extended.tsv.gz
B3DB/__init__.py
B3DB/b3db.py
qc_b3db-1.1.1.dist-info/licenses/LICENSE
qc_b3db-1.1.1.dist-info/METADATA
qc_b3db-1.1.1.dist-info/WHEEL
qc_b3db-1.1.1.dist-info/top_level.txt
qc_b3db-1.1.1.dist-info/zip-safe
qc_b3db-1.1.1.dist-info/RECORD
