Metadata-Version: 2.4
Name: qc-B3DB
Version: 1.1.1
Summary: A rich molecule dataset for Blood-Brain Barrier (BBB) permeability.
Author-email: QC-Devs Community <qcdevs@gmail.com>
License-Expression: CC0-1.0
Project-URL: homepage, https://github.com/theochem/B3DB
Project-URL: documentation, https://github.com/theochem/B3DB
Project-URL: repository, https://github.com/theochem/B3DB
Keywords: Blood-Brain Barrier,BBB,drug discovery,BBB permeability,CNS drug delivery,molecule database
Platform: Linux
Platform: Windows
Platform: MacOS
Classifier: Development Status :: 5 - Production/Stable
Classifier: Environment :: Console
Classifier: Natural Language :: English
Classifier: Operating System :: MacOS
Classifier: Operating System :: Microsoft :: Windows
Classifier: Operating System :: Unix
Classifier: Operating System :: POSIX
Classifier: Operating System :: POSIX :: Linux
Classifier: Programming Language :: Python
Classifier: Programming Language :: Python :: 3
Classifier: Programming Language :: Python :: 3.9
Classifier: Programming Language :: Python :: 3.10
Classifier: Programming Language :: Python :: 3.11
Classifier: Programming Language :: Python :: 3.12
Classifier: Programming Language :: Python :: 3.13
Classifier: Programming Language :: Python :: 3.14
Classifier: Topic :: Scientific/Engineering
Classifier: Topic :: Scientific/Engineering :: Chemistry
Requires-Python: >=3.9
License-File: LICENSE
Requires-Dist: pandas>=1.2.1
Dynamic: license-file
